htmlreport/__init__.py
htmlreport/css/report.css
htmlreport/css/tabby.css
htmlreport/helper.py
htmlreport/javascript.py
htmlreport/report.py
htmlreport/share.py
htmlreport/tabby.py
html_data_report-0.2.0.dist-info/LICENSE
html_data_report-0.2.0.dist-info/METADATA
html_data_report-0.2.0.dist-info/WHEEL
html_data_report-0.2.0.dist-info/RECORD
