Metadata-Version: 2.1
Name: html-data-report
Version: 0.2.0
Summary: This package should be used to create HTML reports that summarise the results of data analyses.
Home-page: https://github.com/ben-j-barlow/html-report
License: GNU LGPLv2.1
Keywords: html,report,visualisation
Author: Ben Barlow
Author-email: ben.j.barlow.1@gmail.com
Requires-Python: >=3.9,<4.0
Classifier: Development Status :: 3 - Alpha
Classifier: License :: OSI Approved :: GNU Lesser General Public License v2 or later (LGPLv2+)
Classifier: License :: Other/Proprietary License
Classifier: Natural Language :: English
Classifier: Operating System :: OS Independent
Classifier: Programming Language :: Python :: 3
Classifier: Programming Language :: Python :: 3.9
Classifier: Programming Language :: Python :: 3.10
Classifier: Programming Language :: Python :: 3.11
Classifier: Programming Language :: Python :: 3.12
Classifier: Programming Language :: Python :: 3.13
Classifier: Topic :: Scientific/Engineering :: Visualization
Classifier: Typing :: Typed
Requires-Dist: dominate (==2.6.0)
Requires-Dist: jinja2 (>=3.1.4,<4.0.0)
Requires-Dist: markdown (>=3.7,<4.0)
Requires-Dist: matplotlib (>=3.9.3,<4.0.0)
Requires-Dist: pandas (>=2.2.3,<3.0.0)
Requires-Dist: plotly (>=5.24.1,<6.0.0)
Project-URL: Repository, https://github.com/ben-j-barlow/html-report
